gbtoolbox/Makefile
gbtoolbox/__init__.py
gbtoolbox/bounds.py
gbtoolbox/dft.py
gbtoolbox/ft_tools.c
gbtoolbox/gen_ztw.c
gbtoolbox/libft.so
gbtoolbox/libztw.so
gbtoolbox/misc.py
gbtoolbox/nn.py
gbtoolbox-0.0.5.dist-info/METADATA
gbtoolbox-0.0.5.dist-info/WHEEL
gbtoolbox-0.0.5.dist-info/licenses/LICENSE
gbtoolbox-0.0.5.dist-info/RECORD
