Metadata-Version: 2.4
Name: gbtoolbox
Version: 0.0.5
Summary: Tools for neural network generalization bounds
Project-URL: Homepage, https://github.com/jonmiller3/Generalization_Bound_Toolbox
Author-email: Jonathan Miller <jon@euler-sci.com>, Thomas Reinke <tom@euler-sci.com>
License-File: LICENSE
Classifier: License :: OSI Approved :: MIT License
Classifier: Operating System :: OS Independent
Classifier: Programming Language :: Python :: 3
Requires-Python: >=3.7
Requires-Dist: geomloss>=0.2.6
Requires-Dist: numba>=0.57.0
Requires-Dist: numpy>=1.24.3
Requires-Dist: scipy>=1.10.1
Requires-Dist: torch>=2.0.1
Provides-Extra: gpu11
Requires-Dist: cupy-cuda11x; extra == 'gpu11'
Provides-Extra: gpu12
Requires-Dist: cupy-cuda12x; extra == 'gpu12'
